[
    {
        "category": "特效種子",
        "tab": "effectSeed",
        "active": true,
        "list": [
            {
                "name": "香蕉皮種子",
                "jpName": "スッテンバナナの種",
                "checked": false,
                "sellStart": "プリベラの森攻略後",
                "notion": "地面に植えるとバナナが現れ、転ばしてくれる。壊れても一日で元通り。",
                "buy": 2200,
                "sell": 1100,
                "id": 1
            },
            {
                "name": "腐爛的香蕉種子",
                "jpName": "腐ったバナナの種",
                "checked": false,
                "notion": "スッテンバナナの種は疲れて眠りについてしまった。「うーん、あと1日･･････。」",
                "buy": 2200,
                "sell": 550,
                "id": 2
            },
            {
                "name": "破掉的蓮葉種子",
                "jpName": "折れたハスの種",
                "checked": false,
                "notion": "ハスライダーの種は疲れて眠りについてしまった。「うーん、あと1日･･････。」",
                "buy": 3200,
                "sell": 800,
                "id": 3
            },
            {
                "name": "蓮葉種子",
                "jpName": "ハスライダーの種",
                "checked": false,
                "sellStart": "ソル・テラーノ砂漠攻略後",
                "notion": "地面に植えるとハスが現れ、乗ると川を渡れる。壊れても一日で元通り。",
                "buy": 3200,
                "sell": 1600,
                "id": 4
            },
            {
                "name": "枯萎的劍草種子",
                "jpName": "しぼんだ剣草の種",
                "checked": false,
                "notion": "剣草の種は疲れて眠りについてしまった。「うーん、あと1日･･････。」",
                "buy": 4800,
                "sell": 1200,
                "id": 5
            },
            {
                "name": "劍草種子",
                "jpName": "剣草の種",
                "checked": false,
                "sellStart": "最初から",
                "notion": "地面に植えると植物の剣が現れ、君を助けてくれる。壊れても一日で元通り。",
                "buy": 4800,
                "sell": 2400,
                "id": 6
            },
            {
                "name": "追風草種子",
                "jpName": "追風草の種",
                "checked": false,
                "sellStart": "ソル・テラーノ砂漠攻略後",
                "notion": "地面に植えると植物の風車が現れ、君を後押ししてくれる。壊れても一日で元通り。",
                "buy": 5000,
                "sell": 2500,
                "id": 7
            },
            {
                "name": "停下的追風草種子",
                "jpName": "止まった追風草の種",
                "checked": false,
                "notion": "追風草の種は疲れて眠りについてしまった。「うーん、あと1日･･････。」",
                "buy": 5000,
                "sell": 1250,
                "id": 8
            },
            {
                "name": "蜜瓜炸彈種子",
                "jpName": "爆弾メロンの種",
                "checked": false,
                "sellStart": "ソル・テラーノ砂漠攻略後",
                "notion": "地面に植えると植物の爆弾が現れ、君を助けてくれる。壊れても一日で元通り。",
                "buy": 5000,
                "sell": 2500,
                "id": 9
            },
            {
                "name": "壞掉的蜜瓜種子",
                "jpName": "壊れたメロンの種",
                "checked": false,
                "notion": "爆弾メロンの種は疲れて眠りについてしまった。「うーん、あと1日･･････。」",
                "buy": 5000,
                "sell": 1250,
                "id": 10
            },
            {
                "name": "水廠草種子",
                "jpName": "水場草の種",
                "checked": false,
                "sellStart": "プリベラの森攻略後",
                "notion": "地面に植えると水を湧き出す植物が現れ、じょうろに給水できる。壊れても一日で元通り。",
                "buy": 5100,
                "sell": 2550,
                "id": 11
            },
            {
                "name": "枯掉的水廠草種子",
                "jpName": "枯れた水場草の種",
                "checked": false,
                "notion": "水場草の種は疲れて眠りについてしまった。「うーん、あと1日･･････。」",
                "buy": 5100,
                "sell": 1275,
                "id": 12
            },
            {
                "name": "南瓜燈種子",
                "jpName": "ジャックの種",
                "checked": false,
                "sellStart": "最初から",
                "notion": "地面に植えるとジャックランタンが現れ、君を助けてくれる。壊れても一日で元通り。",
                "buy": 6900,
                "sell": 3450,
                "id": 13
            },
            {
                "name": "無力南瓜燈種子",
                "jpName": "ダメジャックの種",
                "checked": false,
                "notion": "ジャックの種は疲れて眠りについてしまった。「うーん、あと1日･･････。」",
                "buy": 6900,
                "sell": 1725,
                "id": 14
            },
            {
                "name": "鋼身花種子",
                "jpName": "鋼身花の種",
                "checked": false,
                "sellStart": "ソル・テラーノ砂漠攻略後",
                "notion": "地面に植えると植物の盾が現れ、君を守ってくれる。壊れても一日で元通り。",
                "buy": 7400,
                "sell": 3700,
                "id": 15
            },
            {
                "name": "癱軟的鋼身花種子",
                "jpName": "やわい鋼身花の種",
                "checked": false,
                "notion": "鋼身花の種は疲れて眠りについてしまった。「うーん、あと1日･･････。」",
                "buy": 7400,
                "sell": 1850,
                "id": 16
            },
            {
                "name": "土陶仙人掌種子",
                "jpName": "はにわサボテンの種",
                "checked": false,
                "sellStart": "ソル・テラーノ砂漠攻略後",
                "notion": "地面に植えるとサボテンが現れ、君を助けてくれる。壊れても一日で元通り。",
                "buy": 8800,
                "sell": 4400,
                "id": 17
            },
            {
                "name": "枯掉的仙人掌種子",
                "jpName": "枯れたサボテンの種",
                "checked": false,
                "notion": "はにわサボテンの種は疲れて眠りについてしまった。「うーん、あと1日･･････。」",
                "buy": 8800,
                "sell": 2200,
                "id": 18
            },
            {
                "name": "歪曲的蠶豆種子",
                "jpName": "すねたソラマメの種",
                "checked": false,
                "notion": "マジックソラマメの種は疲れて眠りについてしまった。「うーん、あと1日･･････。」",
                "buy": 12800,
                "sell": 3200,
                "id": 19
            },
            {
                "name": "魔法蠶豆種子",
                "jpName": "マジックソラマメの種",
                "checked": false,
                "sellStart": "インヴァエル川攻略後",
                "notion": "地面に植えるとソラマメが現れ、モンスターをアイテムに変身させる。壊れても一日で元通り。",
                "buy": 12800,
                "sell": 6400,
                "id": 20
            }
        ]
    },
    {
        "category": "種子",
        "tab": "seed",
        "active": false,
        "list": [
            {
                "name": "牧草種子",
                "jpName": "牧草の種",
                "checked": false,
                "season": "全",
                "day": 3,
                "crop": 1,
                "sellStart": "最初から",
                "notion": "収穫するとモンスターのエサとなる牧草を手に入れることができる。連作が可能で、次の収穫まで1日かかる。",
                "buy": 300,
                "sell": 30,
                "getItem": "花屋",
                "id": 1
            },
            {
                "name": "托伊藥草種子",
                "jpName": "トイハーブの種",
                "checked": false,
                "season": "春",
                "day": 2,
                "sellStart": "最初から",
                "notion": "成長は早いが、デリケートな花で育てるのに苦労する。食べると疲労が回復する。",
                "buy": 60,
                "sell": 6,
                "getItem": "花屋",
                "id": 2
            },
            {
                "name": "月落草種子",
                "jpName": "ムーンドロップの種",
                "checked": false,
                "season": "春",
                "day": 7,
                "sellStart": "最初から",
                "notion": "簡単に育てることができる花。",
                "buy": 70,
                "sell": 7,
                "getItem": "花屋",
                "id": 3
            },
            {
                "name": "櫻蕪菁種子",
                "jpName": "サクラカブの種",
                "checked": false,
                "season": "春",
                "day": 3,
                "sellStart": "最初から",
                "notion": "キレイなピンク色をしたカブが育つ。育てやすいため入門の種として人気。",
                "buy": 80,
                "sell": 8,
                "getItem": "雜貨店",
                "id": 4
            },
            {
                "name": "捲心菜種子",
                "jpName": "キャベツの種",
                "checked": false,
                "season": "春",
                "day": 6,
                "sellStart": "最初から",
                "notion": "早く育ち、枯れにくいバランスがよい種。",
                "buy": 100,
                "sell": 10,
                "getItem": "雜貨店",
                "id": 5
            },
            {
                "name": "洋蔥種子",
                "jpName": "タマネギの種",
                "checked": false,
                "season": "春",
                "day": 12,
                "sellStart": "プリベラの森攻略後",
                "notion": "簡単に栽培ができ、土を痛めにくい。",
                "buy": 110,
                "sell": 11,
                "getItem": "雜貨店",
                "id": 6
            },
            {
                "name": "櫻草種子",
                "jpName": "サクラ草の種",
                "checked": false,
                "season": "春",
                "day": 6,
                "sellStart": "最初から",
                "notion": "淡いピンクの花を咲かせる。",
                "buy": 120,
                "sell": 12,
                "getItem": "花屋",
                "id": 7
            },
            {
                "name": "草莓種子",
                "jpName": "イチゴの種",
                "checked": false,
                "season": "春",
                "day": 9,
                "crop": 2,
                "sellStart": "プリベラの森攻略後",
                "notion": "甘い果実を実らせる。連作が可能で、次の実まで2日かかる。",
                "buy": 260,
                "sell": 26,
                "getItem": "雜貨店",
                "id": 8
            },
            {
                "name": "燈草種子",
                "jpName": "ランプ草の種",
                "checked": false,
                "season": "春",
                "day": 18,
                "sellStart": "インヴァエル川攻略後",
                "notion": "長い時間をかけて育てていく。主に薬の材量となる。",
                "buy": 480,
                "sell": 48,
                "getItem": "花屋",
                "id": 9
            },
            {
                "name": "藍水晶種子",
                "jpName": "青水晶の種",
                "checked": false,
                "season": "春",
                "day": 16,
                "sellStart": "インヴァエル川攻略後",
                "notion": "時間をかけて育てていく。青い結晶のような種。",
                "buy": 700,
                "sell": 70,
                "getItem": "花屋",
                "id": 10
            },
            {
                "name": "金剛花種子",
                "jpName": "金剛花の種",
                "checked": false,
                "season": "春",
                "day": 27,
                "sellStart": "インヴァエル川攻略後",
                "notion": "長い時間をかけて育てていく。かなり枯れにくいため、根気さえあれば誰にでも育てられる。",
                "buy": 1000,
                "sell": 100,
                "getItem": "花屋",
                "id": 11
            },
            {
                "name": "粉色貓咪種子",
                "jpName": "ピンクキャットの種",
                "checked": false,
                "season": "夏",
                "day": 4,
                "sellStart": "最初から",
                "notion": "夏にまくことができる。育ちが早く簡単に育てることができる花。やや枯れやすい。",
                "buy": 50,
                "sell": 5,
                "getItem": "花屋",
                "id": 12
            },
            {
                "name": "黃瓜種子",
                "jpName": "キュウリの種",
                "checked": false,
                "season": "夏",
                "day": 6,
                "crop": 2,
                "sellStart": "最初から",
                "notion": "連作が可能で、次の実まで2日かかる。",
                "buy": 80,
                "sell": 8,
                "getItem": "雜貨店",
                "id": 13
            },
            {
                "name": "玉米種子",
                "jpName": "トウモロコシの種",
                "checked": false,
                "season": "夏",
                "day": 13,
                "crop": 2,
                "sellStart": "プリベラの森攻略後",
                "notion": "育ちきるまで時間がかかる。連作が可能で、次の実まで2日かかる。",
                "buy": 130,
                "sell": 13,
                "getItem": "雜貨店",
                "id": 14
            },
            {
                "name": "番茄種子",
                "jpName": "トマトの種",
                "checked": false,
                "season": "夏",
                "day": 11,
                "crop": 1,
                "sellStart": "最初から",
                "notion": "栄養価の高いトマトができる。連作が可能で、次の実まで1日かかる。",
                "buy": 140,
                "sell": 14,
                "getItem": "雜貨店",
                "id": 15
            },
            {
                "name": "茄子種子",
                "jpName": "ナスの種",
                "checked": false,
                "season": "夏",
                "day": 9,
                "crop": 2,
                "sellStart": "ソル・テラーノ砂漠攻略後",
                "notion": "連作が可能で、次の実まで2日かかる。",
                "buy": 160,
                "sell": 16,
                "getItem": "雜貨店",
                "id": 16
            },
            {
                "name": "南瓜種子",
                "jpName": "カボチャの種",
                "checked": false,
                "season": "夏",
                "day": 10,
                "sellStart": "プリベラの森攻略後",
                "notion": "夏にまくことができる大きめの野菜。成長日數も枯れにくさもバランスがいい。",
                "buy": 220,
                "sell": 22,
                "getItem": "雜貨店",
                "id": 17
            },
            {
                "name": "野之花火種子",
                "jpName": "野之花火の種",
                "checked": false,
                "season": "夏",
                "day": 6,
                "sellStart": "最初から",
                "notion": "火薬のような黒い種。",
                "buy": 260,
                "sell": 26,
                "getItem": "花屋",
                "id": 18
            },
            {
                "name": "三葉草種子",
                "jpName": "クローバーの種",
                "checked": false,
                "season": "夏",
                "day": 10,
                "sellStart": "インヴァエル川攻略後",
                "notion": "幸せを運ぶ幸運のタネ。とても枯れやすい。",
                "buy": 390,
                "sell": 39,
                "getItem": "花屋",
                "id": 19
            },
            {
                "name": "鐵千輪種子",
                "jpName": "鉄千輪の種",
                "checked": false,
                "season": "夏",
                "day": 25,
                "sellStart": "インヴァエル川攻略後",
                "notion": "長い時間をかけて育てていく。地中の鉄を集める特殊な性質がある。",
                "buy": 420,
                "sell": 42,
                "getItem": "花屋",
                "id": 20
            },
            {
                "name": "綠水晶種子",
                "jpName": "緑水晶の種",
                "checked": false,
                "season": "夏",
                "day": 16,
                "sellStart": "インヴァエル川攻略後",
                "notion": "時間をかけて育てていく。緑の結晶のような種。",
                "buy": 700,
                "sell": 70,
                "getItem": "花屋",
                "id": 21
            },
            {
                "name": "魅藍草種子",
                "jpName": "チャームブルーの種",
                "checked": false,
                "season": "秋",
                "day": 6,
                "sellStart": "最初から",
                "notion": "成長日數、枯れやすさ共にバランスが良いため育てやすい。",
                "buy": 40,
                "sell": 4,
                "getItem": "花屋",
                "id": 22
            },
            {
                "name": "菠菜種子",
                "jpName": "ホウレン草の種",
                "checked": false,
                "season": "秋",
                "day": 2,
                "sellStart": "プリベラの森攻略後",
                "notion": "すぐに育つが、とても枯れやすい。水は毎日欠かさずあげよう。",
                "buy": 60,
                "sell": 6,
                "getItem": "雜貨店",
                "id": 23
            },
            {
                "name": "蕃薯種子",
                "jpName": "サツマイモの種",
                "checked": false,
                "season": "秋",
                "day": 6,
                "crop": 1,
                "sellStart": "プリベラの森攻略後",
                "notion": "連作が可能で、次の実まで1日かかる。枯れにくいため、忙しくて毎日見れなくても実まで育てることができる。",
                "buy": 80,
                "sell": 8,
                "getItem": "雜貨店",
                "id": 24
            },
            {
                "name": "馬鈴薯種子",
                "jpName": "ジャガイモの種",
                "checked": false,
                "season": "秋",
                "day": 3,
                "sellStart": "最初から",
                "notion": "意外にキレイな花を咲かせる。",
                "buy": 90,
                "sell": 9,
                "getItem": "雜貨店",
                "id": 25
            },
            {
                "name": "胡蘿蔔種子",
                "jpName": "ニンジンの種",
                "checked": false,
                "season": "秋",
                "day": 8,
                "sellStart": "最初から",
                "notion": "バランスのよ良い秋野菜。",
                "buy": 100,
                "sell": 10,
                "getItem": "雜貨店",
                "id": 26
            },
            {
                "name": "青椒種子",
                "jpName": "ピーマンの種",
                "checked": false,
                "season": "秋",
                "day": 9,
                "crop": 1,
                "sellStart": "ソル・テラーノ砂漠攻略後",
                "notion": "栄養価の高い野菜。連作が可能で、次の実まで1日かかる。",
                "buy": 150,
                "sell": 15,
                "getItem": "雜貨店",
                "id": 27
            },
            {
                "name": "花紅葉種子",
                "jpName": "花紅葉の種",
                "checked": false,
                "season": "秋",
                "day": 15,
                "sellStart": "インヴァエル川攻略後",
                "notion": "時間をかけて育てていく。赤味のかかっただえんの種。",
                "buy": 440,
                "sell": 44,
                "getItem": "花屋",
                "id": 28
            },
            {
                "name": "劇毒蒲公英種子",
                "jpName": "タンポイズンの種",
                "checked": false,
                "season": "秋",
                "day": 22,
                "sellStart": "インヴァエル川攻略後",
                "notion": "長い時間をかけて育てていく。白くてやわらかい種。",
                "buy": 510,
                "sell": 51,
                "getItem": "花屋",
                "id": 29
            },
            {
                "name": "赤水晶種子",
                "jpName": "赤水晶の種",
                "checked": false,
                "season": "秋",
                "day": 16,
                "sellStart": "インヴァエル川攻略後",
                "notion": "時間をかけて育てていく。赤い結晶のような種。",
                "buy": 700,
                "sell": 70,
                "getItem": "花屋",
                "id": 30
            },
            {
                "name": "大蔥種子",
                "jpName": "ネギの種",
                "checked": false,
                "season": "冬",
                "day": 6,
                "sellStart": "最初から",
                "notion": "育てやすい冬の作物。少し枯れやすい。",
                "buy": 120,
                "sell": 12,
                "getItem": "雜貨店",
                "id": 31
            },
            {
                "name": "蕪菁種子",
                "jpName": "カブの種",
                "checked": false,
                "season": "冬",
                "day": 3,
                "sellStart": "最初から",
                "notion": "初心者にもおすすめのお手軽な野菜。",
                "buy": 130,
                "sell": 13,
                "getItem": "雜貨店",
                "id": 32
            },
            {
                "name": "蘿蔔種子",
                "jpName": "大根の種",
                "checked": false,
                "season": "冬",
                "day": 7,
                "sellStart": "プリベラの森攻略後",
                "notion": "成長日數、枯れやすさともバランスがいい。",
                "buy": 160,
                "sell": 16,
                "getItem": "雜貨店",
                "id": 33
            },
            {
                "name": "白菜種子",
                "jpName": "白菜の種",
                "checked": false,
                "season": "冬",
                "day": 12,
                "sellStart": "プリベラの森攻略後",
                "notion": "育つまでに少し時間がかかる。",
                "buy": 200,
                "sell": 20,
                "getItem": "雜貨店",
                "id": 34
            },
            {
                "name": "樹形草種子",
                "jpName": "ツリー草の種",
                "checked": false,
                "season": "冬",
                "day": 24,
                "sellStart": "インヴァエル川攻略後",
                "notion": "長い時間をかけて育てていく。かなり枯れにくい。",
                "buy": 330,
                "sell": 33,
                "getItem": "花屋",
                "id": 35
            },
            {
                "name": "火熱種子",
                "jpName": "ほかほかの種",
                "checked": false,
                "season": "冬",
                "day": 18,
                "sellStart": "ソル・テラーノ砂漠攻略後",
                "notion": "実になるまでにちょっぴり時間がかかるが枯れにくいので育てやすい。",
                "buy": 470,
                "sell": 47,
                "getItem": "雜貨店",
                "id": 36
            },
            {
                "name": "白水晶種子",
                "jpName": "白水晶の種",
                "checked": false,
                "season": "冬",
                "day": 16,
                "sellStart": "インヴァエル川攻略後",
                "notion": "時間をかけて育てていく。白い結晶のような種。",
                "buy": 700,
                "sell": 70,
                "getItem": "花屋",
                "id": 37
            },
            {
                "name": "金南瓜種子",
                "jpName": "金のカボチャの種",
                "checked": false,
                "day": 15,
                "notion": "ゴージャスな金色のカボチャができる。",
                "buy": 190,
                "sell": 19,
                "id": 38
            },
            {
                "name": "金蕪菁種子",
                "jpName": "金のカブの種",
                "checked": false,
                "day": 5,
                "notion": "ゴージャスな金色のカブができる。",
                "buy": 210,
                "sell": 21,
                "id": 39
            },
            {
                "name": "金捲心菜種子",
                "jpName": "金のキャベツの種",
                "checked": false,
                "day": 14,
                "notion": "ゴージャスな金色のキャベツができる。",
                "buy": 230,
                "sell": 23,
                "id": 40
            },
            {
                "name": "金馬鈴薯種子",
                "jpName": "金のジャガイモの種",
                "checked": false,
                "day": 6,
                "notion": "ゴージャスな金色のジャガイモができる。",
                "buy": 250,
                "sell": 25,
                "id": 41
            },
            {
                "name": "鳳梨種子",
                "jpName": "パイナップルの種",
                "checked": false,
                "day": 14,
                "crop": 3,
                "notion": "育てるのに少し時間のかかる作物。連作が可能で、次の実まで3日かかる。",
                "buy": 300,
                "sell": 30,
                "id": 42
            },
            {
                "name": "少女哈密瓜種子",
                "jpName": "オトメロンの種",
                "checked": false,
                "day": 7,
                "sellStart": "ソル・テラーノ砂漠攻略後",
                "notion": "乙女の甘酸っぱい力をあびてなんともかわいらしい種が誕生した。",
                "buy": 620,
                "sell": 62,
                "getItem": "雜貨店",
                "id": 43
            }
        ]
    },
    {
        "category": "果實",
        "tab": "fruit",
        "active": false,
        "list": [
            {
                "name": "橘子",
                "jpName": "オレンジ",
                "checked": false,
                "sp": [
                    "RP回復+20",
                    "智力+4",
                    "3時間"
                ],
                "notion": "ほどよい甘さとすっぱさをあわせ持つ多才なオレンジボーイ。うっかり食べ過ぎると、色々なところが彼色に染まる",
                "buy": 160,
                "sell": 80,
                "id": 1
            },
            {
                "name": "蘋果",
                "jpName": "リンゴ",
                "checked": false,
                "sp": [
                    "RP回復+10",
                    "智力+2",
                    "3時間"
                ],
                "notion": "真っ赤な果実のスイートプリティーガール。醫者いらずと言われるほど栄養もたくさん。唯一の悩みは、人々をとりこにしすぎる自分自身の魅力。",
                "buy": 120,
                "sell": 60,
                "id": 2
            },
            {
                "name": "葡萄",
                "jpName": "ブドウ",
                "checked": false,
                "sp": [
                    "RP回復+15",
                    "智力+3",
                    "3時間"
                ],
                "notion": "紫色の小さな実が房狀に実った果物。甘い実が集まっている姿は、まさに甘味のカーニバル。",
                "buy": 180,
                "sell": 90,
                "id": 3
            },
            {
                "name": "鳳梨",
                "jpName": "パイナップル",
                "checked": false,
                "sp": [
                    "RP回復+20",
                    "力量+2",
                    "智力+6",
                    "3時間"
                ],
                "notion": "南の國から伝わってきた果物。甘くさわやかな酸味があり、匂いをかげば気分は常夏。",
                "buy": 6000,
                "sell": 1200,
                "id": 4
            },
            {
                "name": "草莓",
                "jpName": "イチゴ",
                "checked": false,
                "sp": [
                    "RP回復+6%",
                    "智力+1",
                    "3時間"
                ],
                "notion": "テーブルの上の赤い妖精。ほの酸っぱい甘さと、ひとくちサイズの実が食したものを魅了する。",
                "buy": 2160,
                "sell": 720,
                "id": 5
            }
        ]
    },
    {
        "category": "花草",
        "tab": "flower",
        "active": false,
        "list": [
            {
                "name": "白水晶",
                "jpName": "白水晶",
                "checked": false,
                "sp": [
                    "HP回復+20%",
                    "RP回復+15%",
                    "3時間"
                ],
                "notion": "ルーンの結晶が地中に集まってできた花。季節で花の色が違い、冬は白い花が開く。",
                "buy": 49000,
                "sell": 7000,
                "id": 1
            },
            {
                "name": "赤水晶",
                "jpName": "赤水晶",
                "checked": false,
                "sp": [
                    "HP回復+20%",
                    "RP回復+15%",
                    "3時間"
                ],
                "notion": "ルーンの結晶が地中に集まってできた花。季節で花の色が違い、秋は赤い花が開く。",
                "buy": 49000,
                "sell": 7000,
                "id": 2
            },
            {
                "name": "劇毒蒲公英",
                "jpName": "タンポイズン",
                "checked": false,
                "sp": [
                    "RP回復+15%"
                ],
                "notion": "中心に白く小さい綿のような花が咲く。綿はかわいく見えても毒を持つので注意。息を軽く吹きかけると、花が風に乗って空を舞うので、さらに危険。",
                "buy": 46200,
                "sell": 6600,
                "id": 3
            },
            {
                "name": "花紅葉",
                "jpName": "花紅葉",
                "checked": false,
                "sp": [
                    "RP回復+15%",
                    "HP上限+5%"
                ],
                "notion": "鮮やかな色の花を咲かせる草。花がまるで紅葉してるように見えるため花紅葉と呼ばれるようになった。",
                "buy": 37800,
                "sell": 5400,
                "id": 4
            },
            {
                "name": "樹形草",
                "jpName": "ツリー草",
                "checked": false,
                "sp": [
                    "RP回復+15%",
                    "體力+12",
                    "3時間"
                ],
                "notion": "草なのに木の形をした草。冬になると、ツリー草に飾りつけをしてテーブルの上にも置いたりする。",
                "buy": 29547,
                "sell": 4221,
                "id": 5
            },
            {
                "name": "綠水晶",
                "jpName": "緑水晶",
                "checked": false,
                "sp": [
                    "HP回復+20%",
                    "RP回復+15%",
                    "3時間"
                ],
                "notion": "ルーンの結晶が地中に集まってできた花。季節で花の色が違い、夏は緑の花が開く。",
                "buy": 49000,
                "sell": 7000,
                "id": 6
            },
            {
                "name": "野之花火",
                "jpName": "野之花火",
                "checked": false,
                "sp": [
                    "RP回復+15%",
                    "力量+10%",
                    "3時間"
                ],
                "notion": "花の形がとても特徴的。『野山に咲く花火』として親しまれている。耳をすませば花火の音が。",
                "buy": 8400,
                "sell": 1200,
                "id": 7
            },
            {
                "name": "四葉三葉草",
                "jpName": "四つ葉のクローバー",
                "checked": false,
                "sp": [
                    "RP回復+15%",
                    "3時間"
                ],
                "notion": "幸せのラッキーアイテム。持っていてもハッピー。プレゼントとしてもハッピーで、ハッピッピー。",
                "buy": 14700,
                "sell": 2100,
                "id": 8
            },
            {
                "name": "鐵千輪",
                "jpName": "鉄千輪",
                "checked": false,
                "sp": [
                    "HP回復-25%",
                    "RP回復+15%",
                    "力量+12",
                    "體力-4",
                    "3時間"
                ],
                "notion": "とげとげの形をした草。中心にある草が、地中の鉄分を集め特徴的な形狀を作り出す。",
                "buy": 38500,
                "sell": 5500,
                "id": 9
            },
            {
                "name": "金剛花",
                "jpName": "金剛花",
                "checked": false,
                "sp": [
                    "HP回復+50%",
                    "RP回復+15%",
                    "體力+15",
                    "3時間"
                ],
                "notion": "すべてが金色の花。とても頑丈な花で、枯れにくい。見た目通り硬く、転んだ先に生えていると痛い思いをする。",
                "buy": 89600,
                "sell": 12800,
                "id": 10
            },
            {
                "name": "青水晶",
                "jpName": "青水晶",
                "checked": false,
                "sp": [
                    "HP回復+20%",
                    "RP回復+15%",
                    "3時間"
                ],
                "notion": "ルーンの結晶が地中に集まってできた花。季節で花の色が違い、春は青の花が開く。",
                "buy": 49000,
                "sell": 7000,
                "id": 11
            },
            {
                "name": "燈草",
                "jpName": "ランプ草",
                "checked": false,
                "sp": [
                    "HP回復+10%",
                    "RP回復+15%",
                    "3時間"
                ],
                "notion": "つぼみの中には、輝く粉がつまっている。見ていると、とても落ち著いた気分になり、リラックスさせる効果があるのかも。",
                "buy": 32060,
                "sell": 4580,
                "id": 12
            },
            {
                "name": "櫻草",
                "jpName": "サクラ草",
                "checked": false,
                "sp": [
                    "RP回復+15%",
                    "3時間"
                ],
                "notion": "ピンクの花をつける植物。春の風物詩。",
                "buy": 6020,
                "sell": 860,
                "id": 13
            },
            {
                "name": "枯草",
                "jpName": "枯草",
                "checked": false,
                "sp": [
                    "RP回復-50%"
                ],
                "notion": "食べると毒になってしまう枯れた草。枯草と一緒に耕すと、土質が良くなる。後に枯草は、こう語っているという。「枯れたとしても、私には未來がある」と。",
                "buy": 8,
                "sell": 1,
                "id": 14
            },
            {
                "name": "雜草",
                "jpName": "雑草",
                "checked": false,
                "sp": [
                    "HP回復-5"
                ],
                "notion": "どこにでもいつでもどんな時も。いつもはきらわれ者だけど、強く生きるその姿勢に心打たれた人も多いとか。",
                "buy": 10,
                "sell": 1,
                "id": 15
            },
            {
                "name": "白草",
                "jpName": "白い草",
                "checked": false,
                "sp": [
                    "HP回復+3",
                    "PR回復+3"
                ],
                "notion": "うつくしい純白の草。雪とまざって見つけにくいため、気がつかない人も多い。はかなくも気高い草。",
                "buy": 90,
                "sell": 5,
                "id": 16
            },
            {
                "name": "藍草",
                "jpName": "藍の草",
                "checked": false,
                "sp": [
                    "HP回復+3",
                    "PR回復+3"
                ],
                "notion": "見ているとなぜか落ち著く草。ケンカをしている人たちの足元に、ひっそりと生え、仲直りさせたという伝説がある。",
                "buy": 30,
                "sell": 5,
                "id": 17
            },
            {
                "name": "紫草",
                "jpName": "紫の草",
                "checked": false,
                "sp": [
                    "HP回復+3",
                    "PR回復+3"
                ],
                "notion": "上品な草。色草の中でも、プライドが高く、お上品。それゆえか、他の草とは仲が悪い。",
                "buy": 30,
                "sell": 5,
                "id": 18
            },
            {
                "name": "綠草",
                "jpName": "緑の草",
                "checked": false,
                "sp": [
                    "HP回復+3",
                    "PR回復+3"
                ],
                "notion": "グリーンな草、つまり普通の草。色草の中でも個性がないと言われ続け、そんな自分を変えようと努力している。",
                "buy": 30,
                "sell": 5,
                "id": 19
            },
            {
                "name": "青草",
                "jpName": "青い草",
                "checked": false,
                "sp": [
                    "HP回復+3",
                    "PR回復+3"
                ],
                "notion": "クールな草。さわると少しひんやりとしている。落ち著く効果があると言われ、薬品などにも使われる。",
                "buy": 30,
                "sell": 5,
                "id": 20
            },
            {
                "name": "黃草",
                "jpName": "黃の草",
                "checked": false,
                "sp": [
                    "HP回復+3",
                    "PR回復+3"
                ],
                "notion": "幸運を呼ぶと言われている草。主に金運がアップするとして、お守りかわりに持つ人もいる。",
                "buy": 30,
                "sell": 5,
                "id": 21
            },
            {
                "name": "紅草",
                "jpName": "赤い草",
                "checked": false,
                "sp": [
                    "HP回復+3",
                    "PR回復+3"
                ],
                "notion": "じょうねつの草。昔から赤色は成長を早める効果があると言われていて、他の草より早く育つ。",
                "buy": 30,
                "sell": 5,
                "id": 22
            },
            {
                "name": "太陽草",
                "jpName": "だいだい草",
                "checked": false,
                "sp": [
                    "HP回復+3",
                    "PR回復+3"
                ],
                "notion": "夏の太陽を思わせる草。そのまぶしく鮮やかな色は、見ているだけでも元気になれる。",
                "buy": 30,
                "sell": 5,
                "id": 23
            },
            {
                "name": "黑草",
                "jpName": "黒い草",
                "checked": false,
                "sp": [
                    "HP回復+3",
                    "PR回復+3"
                ],
                "notion": "あやしく黒光りする草。夜になると、どこにあるかわからなくなってしまうため、よく踏まれてしまう。",
                "buy": 90,
                "sell": 5,
                "id": 24
            },
            {
                "name": "解毒草",
                "jpName": "毒消し草",
                "checked": false,
                "sp": [
                    "HP回復+5"
                ],
                "notion": "體中の毒を浄化する草。とても苦い。苦くて「ぐえ」となるが、食べると毒が治る。背に腹は変えられない。",
                "buy": 60,
                "sell": 6,
                "id": 25
            },
            {
                "name": "藥草",
                "jpName": "薬草",
                "checked": false,
                "sp": [
                    "HP回復+20"
                ],
                "notion": "野生する薬草。苦くて「うえ」となるが、食べると回復する。どっちを取るかはあなた次第。",
                "buy": 80,
                "sell": 8,
                "id": 26
            },
            {
                "name": "魅藍草",
                "jpName": "チャームブルー",
                "checked": false,
                "sp": [
                    "HP回復+5%",
                    "RP回復+15%",
                    "3時間"
                ],
                "notion": "深い青色をした草。つぼみがとても大きく、色とあわせて、吸い込まれてしまいそうになる。",
                "buy": 2240,
                "sell": 320,
                "id": 27
            },
            {
                "name": "粉色貓咪",
                "jpName": "ピンクキャット",
                "checked": false,
                "sp": [
                    "HP回復+6%",
                    "RP回復+15%",
                    "3時間"
                ],
                "notion": "鮮やかなピンク色の草。つぼみが小さく、かわいらしいため、「キャット」の名で呼ばれるようになった。",
                "buy": 1890,
                "sell": 270,
                "id": 28
            },
            {
                "name": "月落草",
                "jpName": "ムーンドロップ",
                "checked": false,
                "sp": [
                    "RP回復+15%",
                    "智力+6%",
                    "3時間"
                ],
                "notion": "月明かりで育つ不思議な草。月から零れ落ちてきたかのような美しい黃色い花が咲く。",
                "buy": 4200,
                "sell": 600,
                "id": 29
            },
            {
                "name": "托伊藥草",
                "jpName": "トイハーブ",
                "checked": false,
                "sp": [
                    "HP回復+2%",
                    "RP回復+15%",
                    "3時間"
                ],
                "notion": "健康にいいとされる薬味。育てるのが少し大変。食べると疲労を治す。",
                "buy": 1260,
                "sell": 180,
                "id": 30
            }
        ]
    },
    {
        "category": "野菜",
        "tab": "vegetables",
        "active": false,
        "list": [
            {
                "name": "蘑菇",
                "jpName": "きのこ",
                "checked": false,
                "sp": [
                    "HP回復+100%",
                    "RP回復+50%",
                    "風邪"
                ],
                "notion": "その辺りに生えていたきのこ。食べても大丈夫かどうかは君の身體のみが知る。",
                "buy": 100,
                "sell": 10,
                "id": 1
            },
            {
                "name": "蘑菇",
                "jpName": "きのこ",
                "checked": false,
                "sp": [
                    "HP回復+100%",
                    "RP回復+50%",
                    "眠り"
                ],
                "notion": "その辺りに生えていたきのこ。食べても大丈夫かどうかは君の身體のみが知る。",
                "buy": 100,
                "sell": 10,
                "id": 2
            },
            {
                "name": "蘑菇",
                "jpName": "きのこ",
                "checked": false,
                "sp": [
                    "HP回復+100",
                    "RP回復+50",
                    "マヒ"
                ],
                "notion": "その辺りに生えていたきのこ。食べても大丈夫かどうかは君の身體のみが知る。",
                "buy": 100,
                "sell": 10,
                "id": 3
            },
            {
                "name": "蘑菇",
                "jpName": "きのこ",
                "checked": false,
                "sp": [
                    "HP回復+100",
                    "RP回復+50",
                    "毒"
                ],
                "notion": "その辺りに生えていたきのこ。食べても大丈夫かどうかは君の身體のみが知る。",
                "buy": 100,
                "sell": 10,
                "id": 4
            },
            {
                "name": "蘑菇",
                "jpName": "きのこ",
                "checked": false,
                "sp": [
                    "HP回復+100%",
                    "RP回復+50%"
                ],
                "notion": "その辺りに生えていたきのこ。食べても大丈夫かどうかは君の身體のみが知る。",
                "buy": 100,
                "sell": 10,
                "id": 5
            },
            {
                "name": "蘑菇",
                "jpName": "きのこ",
                "checked": false,
                "sp": [
                    "HP回復+100",
                    "RP回復+50",
                    "狀態異常回復"
                ],
                "notion": "その辺りに生えていたきのこ。食べても大丈夫かどうかは君の身體のみが知る。",
                "buy": 100,
                "sell": 10,
                "id": 6
            },
            {
                "name": "金蕪菁",
                "jpName": "金のカブ",
                "checked": false,
                "sp": [
                    "HP回復+30",
                    "RP回復+10",
                    "RP+20",
                    "力量-8",
                    "智力+7"
                ],
                "notion": "世にも珍しい金色の野菜。自分の髪の毛と同じ色のカブが欲しい、というリクエストによって作られたという。",
                "buy": 7000,
                "sell": 1400,
                "id": 7
            },
            {
                "name": "金馬鈴薯",
                "jpName": "金のジャガイモ",
                "checked": false,
                "sp": [
                    "HP回復+15",
                    "RP回復+25",
                    "力量+3",
                    "體力+3",
                    "智力+2"
                ],
                "notion": "世にも珍しい金色の野菜。地面に埋まっていても光がもれているため場所がわかりやすい。",
                "buy": 9500,
                "sell": 1900,
                "id": 8
            },
            {
                "name": "金南瓜",
                "jpName": "金のカボチャ",
                "checked": false,
                "sp": [
                    "HP回復+70",
                    "HP上限+30",
                    "體力+6"
                ],
                "notion": "世にも珍しい金色の野菜。飾りつけをしなくてもくりぬくだけで、十分お化けに見えてしまう。",
                "buy": 16500,
                "sell": 3300,
                "id": 9
            },
            {
                "name": "金捲心菜",
                "jpName": "金のキャベツ",
                "checked": false,
                "sp": [
                    "HP回復+50",
                    "HP上限+50",
                    "體力+6",
                    "3時間"
                ],
                "notion": "世にも珍しい金色の野菜。突然、ふしぎな力がわいてきて変色した。甘さも數倍パワーアップ！",
                "buy": 19000,
                "sell": 3800,
                "id": 10
            },
            {
                "name": "竹筍",
                "jpName": "タケノコ",
                "checked": false,
                "sp": [
                    "HP回復+5",
                    "RP回復+15",
                    "HP上限+3",
                    "RP上限+3",
                    "力量+1",
                    "智力+1",
                    "3時間"
                ],
                "notion": "コリコリした食感と香ばしい味の野菜。成長が早く、春にはたくさんのタケノコが畑に芽を出す。芽が非常に強く、石をも突き破る。",
                "buy": 300,
                "sell": 12,
                "id": 11
            },
            {
                "name": "火熱果實",
                "jpName": "ほかほかの実",
                "checked": false,
                "sp": [
                    "HP回復+50",
                    "RP回復+50",
                    "體力+8",
                    "智力-4",
                    "3時間"
                ],
                "notion": "毛に包まれたような野菜。一部の地方では、お風呂を沸かすときほかほかの実を使用するという。火屬性のダメージを半減する。",
                "buy": 24000,
                "sell": 4800,
                "id": 12
            },
            {
                "name": "白菜",
                "jpName": "白菜",
                "checked": false,
                "sp": [
                    "HP回復+15",
                    "RP回復+30",
                    "體力+5",
                    "智力-2",
                    "3時間"
                ],
                "notion": "冬に旬を迎える野菜。寒ければ寒いほど甘みを出す。という、逆境をバネにする気合の持ち主。",
                "buy": 5400,
                "sell": 1350,
                "id": 13
            },
            {
                "name": "大蔥",
                "jpName": "ネギ",
                "checked": false,
                "sp": [
                    "HP回復+5",
                    "RP回復+10",
                    "力量+2",
                    "3時間"
                ],
                "notion": "冬の汁物にはかかせない野菜。「コケホッホーがネギしょってきた」ということわざがある。",
                "buy": 1500,
                "sell": 500,
                "id": 14
            },
            {
                "name": "蘿蔔",
                "jpName": "大根",
                "checked": false,
                "sp": [
                    "HP回復+5",
                    "RP回復+20",
                    "3時間"
                ],
                "notion": "白くて太いセクシーな野菜。味にクセがないため、色々な場面にさりげなく登場して、みんなを安心させる。",
                "buy": 2310,
                "sell": 770,
                "id": 15
            },
            {
                "name": "蕪菁",
                "jpName": "カブ",
                "checked": false,
                "sp": [
                    "HP回復+10",
                    "RP回復+5",
                    "力量-2",
                    "智力+3",
                    "3時間"
                ],
                "notion": "言わずと知れた牧場の王道。王者への道はきびしく、數々の試練を様々なテクニックで乗り越えてきた。",
                "buy": 1260,
                "sell": 420,
                "id": 16
            },
            {
                "name": "菠菜",
                "jpName": "ホウレン草",
                "checked": false,
                "sp": [
                    "HP回復+5",
                    "RP回復+10",
                    "HP上限+3",
                    "力量+3",
                    "體力+1",
                    "智力-2",
                    "3時間"
                ],
                "notion": "濃い緑色に豊富な栄養を含んだ野菜。缶詰になったものを食べると強くて元気になる伝説がある。",
                "buy": 340,
                "sell": 140,
                "id": 17
            },
            {
                "name": "青椒",
                "jpName": "ピーマン",
                "checked": false,
                "sp": [
                    "RP回復+15",
                    "RP上限+10",
                    "3時間"
                ],
                "notion": "苦味があるため、嫌われがちなピーマン。実はとてもさびしがり屋で、そんな事実に影でこっそり泣いている。俺だって本當はおいしいんだ。",
                "buy": 930,
                "sell": 310,
                "id": 18
            },
            {
                "name": "胡蘿蔔",
                "jpName": "ニンジン",
                "checked": false,
                "sp": [
                    "RP回復+15",
                    "3時間"
                ],
                "notion": "オレンジ色で細長い野菜。目の前にぶらさげると突進力が大幅にアップすると言われている。",
                "buy": 1770,
                "sell": 590,
                "id": 19
            },
            {
                "name": "馬鈴薯",
                "jpName": "ジャガイモ",
                "checked": false,
                "sp": [
                    "HP回復+5",
                    "RP回復+5",
                    "3時間"
                ],
                "notion": "広く親しまれている野菜。さまざまな料理に使われ、主食から前菜まで幅広く活躍するが、控えめに「そんなことないッス」と否定している。",
                "buy": 840,
                "sell": 280,
                "id": 20
            },
            {
                "name": "蕃薯",
                "jpName": "サツマイモ",
                "checked": false,
                "sp": [
                    "HP上限+10",
                    "體力+5",
                    "3時間"
                ],
                "notion": "別名「ミスターおなら」食物繊維を多く含み、お腹の中をキレイにしてくれる野菜。",
                "buy": 440,
                "sell": 40,
                "id": 21
            },
            {
                "name": "茄子",
                "jpName": "ナス",
                "checked": false,
                "sp": [
                    "HP回復+15",
                    "RP回復+10",
                    "體力+5",
                    "3時間"
                ],
                "notion": "紫のニヒルボーイと言ったらこいつのこと。ふにゃっとしたヘタがかわいいが、考えていることはずっと大人。",
                "buy": 1040,
                "sell": 480,
                "id": 22
            },
            {
                "name": "番茄",
                "jpName": "トマト",
                "checked": false,
                "sp": [
                    "HP回復+15",
                    "RP回復+10",
                    "3時間"
                ],
                "notion": "輝く赤が夏の太陽を思わせる。栄養価がとても高く、健康にも良い。生食する場合は、主に冷やして食べる。ぜひ冬に食べてみよう、何もないけど。",
                "buy": 900,
                "sell": 300,
                "id": 23
            },
            {
                "name": "玉米",
                "jpName": "トウモロコシ",
                "checked": false,
                "sp": [
                    "HP回復+25",
                    "RP回復+10",
                    "HP上限+10",
                    "RP上限+10",
                    "3時間"
                ],
                "notion": "黃色く小さい実がぎっしりとつまった野菜。一粒一粒もトウモロコシで、しばしばどこから食べられるべきか、ケンカする。",
                "buy": 1320,
                "sell": 440,
                "id": 24
            },
            {
                "name": "黃瓜",
                "jpName": "キュウリ",
                "checked": false,
                "sp": [
                    "HP回復+10",
                    "RP回復+10",
                    "HP上限+5",
                    "RP上限+10",
                    "3時間"
                ],
                "notion": "カリっと歯ごたえがナイスガイ。水分を多く含むため、冷靜になろうよ、という意味で「キューリにいこうぜ」と言う。キューリに行こうぜ？",
                "buy": 720,
                "sell": 180,
                "id": 25
            },
            {
                "name": "南瓜",
                "jpName": "カボチャ",
                "checked": false,
                "sp": [
                    "HP回復+50",
                    "HP上限+30",
                    "體力+3",
                    "3時間"
                ],
                "notion": "黃色い野菜に栄養がたくさんつまった野菜。秋のお祭りでは中身をくり抜き、お化けへの変身グッズになる。",
                "buy": 4960,
                "sell": 1240,
                "id": 26
            },
            {
                "name": "洋蔥",
                "jpName": "タマネギ",
                "checked": false,
                "sp": [
                    "HP回復+20",
                    "RP回復+30",
                    "HP上限+5",
                    "3時間"
                ],
                "notion": "生では、ツンとした辛味、加熱すればほどよく甘い忙しいお野菜。辛かったり甘かったり、切る時涙したり、別にあんたのためじゃないんだからね。",
                "buy": 3120,
                "sell": 780,
                "id": 27
            },
            {
                "name": "少女哈密瓜",
                "jpName": "オトメロン",
                "checked": false,
                "sp": [
                    "HP回復+50",
                    "RP回復+30",
                    "HP上限+5",
                    "3時間"
                ],
                "notion": "乙女パワーを十分にあびた、ピンク色のかわいいかわいいメロン。もちろん味も乙女の保証付き。オトメ星雲より乙女パワーがふりそそぐ！",
                "buy": 12600,
                "sell": 4200,
                "id": 28
            },
            {
                "name": "櫻蕪菁",
                "jpName": "サクラカブ",
                "checked": false,
                "sp": [
                    "HP回復+5",
                    "RP回復+5",
                    "3時間"
                ],
                "notion": "キレイなピンク色のカブ。地方の違いで白いカブしか育たなかったがある少女の努力により、改良に成功した。",
                "buy": 400,
                "sell": 200,
                "id": 29
            },
            {
                "name": "捲心菜",
                "jpName": "キャベツ",
                "checked": false,
                "sp": [
                    "HP回復+10",
                    "HP上限+10",
                    "體力+2",
                    "3時間"
                ],
                "notion": "生、焼、煮と、バランスの良い野菜。食前でも食中でも食後でも活躍する。胃の調子を整える効果がある。食べすぎにはキャベツ。",
                "buy": 1920,
                "sell": 480,
                "id": 30
            }
        ]
    },
    {
        "category": "食材",
        "tab": "ingredients",
        "active": false,
        "list": [
            {
                "name": "丸子粉",
                "jpName": "だんご粉",
                "checked": false,
                "sp": [
                    "HP回復+5"
                ],
                "buy": 80,
                "sell": 40,
                "id": 1
            },
            {
                "name": "咖喱粉",
                "jpName": "カレー粉",
                "checked": false,
                "sp": [
                    "HP回復-20",
                    "力量+2",
                    "火屬性のダメージを半減"
                ],
                "buy": 140,
                "sell": 70,
                "id": 2
            },
            {
                "name": "油",
                "jpName": "油",
                "checked": false,
                "sp": [
                    "HP回復-50%",
                    "RP回復-25%",
                    "體力+5",
                    "火屬性にかなり弱くなる"
                ],
                "buy": 500,
                "sell": 250,
                "id": 3
            },
            {
                "name": "小麥粉",
                "jpName": "小麥粉",
                "checked": false,
                "sp": [
                    "HP回復-20",
                    "HP上限+1"
                ],
                "buy": 250,
                "sell": 125,
                "id": 4
            },
            {
                "name": "蜂蜜",
                "jpName": "ハチミツ",
                "checked": false,
                "sp": [
                    "HP回復+35%",
                    "RP回復20%",
                    "力量-4",
                    "體力-2"
                ],
                "buy": 1000,
                "sell": 680,
                "id": 5
            },
            {
                "name": "每日健康蛋",
                "jpName": "毎日ケンコー卵",
                "checked": false,
                "sp": [
                    "HP回復+30",
                    "力量+3",
                    "封印を少し受けにくくなる"
                ],
                "buy": 960,
                "sell": 480,
                "id": 6
            },
            {
                "name": "優質蛋",
                "jpName": "良い卵",
                "checked": false,
                "sp": [
                    "HP回復+20",
                    "力量+2",
                    "封印をわずかに受けにくくなる"
                ],
                "buy": 760,
                "sell": 380,
                "id": 7
            },
            {
                "name": "蛋",
                "jpName": "卵",
                "checked": false,
                "sp": [
                    "HP回復+10",
                    "力量+1",
                    "封印をわずかに受けにくくなる"
                ],
                "buy": 560,
                "sell": 280,
                "id": 8
            },
            {
                "name": "鈣滿點牛奶",
                "jpName": "カルシウム満點牛乳",
                "checked": false,
                "sp": [
                    "HP回復+90",
                    "體力+3",
                    "毒を少し受けにくくなる"
                ],
                "buy": 1000,
                "sell": 500,
                "id": 9
            },
            {
                "name": "優質牛奶",
                "jpName": "良い牛乳",
                "checked": false,
                "sp": [
                    "HP回復+60",
                    "體力+2",
                    "毒をわずかに受けにくくなる"
                ],
                "buy": 760,
                "sell": 380,
                "id": 10
            },
            {
                "name": "牛奶",
                "jpName": "牛乳",
                "checked": false,
                "sp": [
                    "HP回復+30",
                    "體力+1",
                    "毒をわずかに受けにくくなる"
                ],
                "buy": 520,
                "sell": 260,
                "id": 11
            },
            {
                "name": "艾麗草",
                "jpName": "エリ草",
                "checked": false,
                "sp": [
                    "HP上限+1",
                    "智力+2"
                ],
                "buy": 750,
                "sell": 250,
                "id": 12
            },
            {
                "name": "紅酒",
                "jpName": "ワイン",
                "checked": false,
                "sp": [
                    "HP回復+100",
                    "RP回復+40",
                    "力量-3",
                    "體力-2",
                    "智力-2",
                    "クリティカルを受けにくくなる"
                ],
                "buy": 1600,
                "sell": 800,
                "id": 13
            },
            {
                "name": "巧克力",
                "jpName": "チョコレート",
                "checked": false,
                "sp": [
                    "RP回復+10%",
                    "智力+2"
                ],
                "buy": 450,
                "sell": 150,
                "id": 14
            },
            {
                "name": "米飯",
                "jpName": "ごはん",
                "checked": false,
                "sp": [
                    "HP回復+30",
                    "HP上限+5"
                ],
                "buy": 100,
                "sell": 50,
                "id": 15
            }
        ]
    },
    {
        "category": "魚",
        "tab": "fish",
        "active": false,
        "list": [
            {
                "name": "公魚",
                "jpName": "ワカサギ",
                "checked": false,
                "season": "冬",
                "MaxCM": 10,
                "id": 1
            },
            {
                "name": "螢烏賊",
                "jpName": "フーインイカ",
                "checked": false,
                "season": "春",
                "MaxCM": 10,
                "buy": 21000,
                "sell": 2100,
                "id": 2
            },
            {
                "name": "蝦",
                "jpName": "エビ",
                "checked": false,
                "season": "夏",
                "MaxCM": 10,
                "buy": 1800,
                "sell": 180,
                "id": 3
            },
            {
                "name": "沙丁魚",
                "jpName": "イワシ",
                "checked": false,
                "season": "夏",
                "MaxCM": 10,
                "buy": 1400,
                "sell": 140,
                "id": 4
            },
            {
                "name": "斑鲅魚",
                "jpName": "メジナ",
                "checked": false,
                "season": "冬",
                "MaxCM": 30,
                "id": 5
            },
            {
                "name": "真鱒魚",
                "jpName": "ヤマメ",
                "checked": false,
                "season": "春",
                "MaxCM": 30,
                "buy": 700,
                "sell": 70,
                "id": 6
            },
            {
                "name": "針魚",
                "jpName": "サヨリ",
                "checked": false,
                "season": "春",
                "MaxCM": 30,
                "id": 7
            },
            {
                "name": "銀鮒魚",
                "jpName": "ギンブナ",
                "checked": false,
                "season": "春",
                "MaxCM": 30,
                "id": 8
            },
            {
                "name": "鱒魚",
                "jpName": "アマゴ",
                "checked": false,
                "season": "春",
                "MaxCM": 30,
                "buy": 600,
                "sell": 60,
                "id": 9
            },
            {
                "name": "雅羅魚",
                "jpName": "ウグイ",
                "checked": false,
                "season": "夏",
                "MaxCM": 30,
                "id": 10
            },
            {
                "name": "巖魚",
                "jpName": "イワナ",
                "checked": false,
                "season": "夏",
                "MaxCM": 30,
                "buy": 2000,
                "sell": 200,
                "id": 11
            },
            {
                "name": "河豚",
                "jpName": "フグ",
                "checked": false,
                "season": "冬",
                "MaxCM": 60,
                "buy": 57000,
                "sell": 5700,
                "id": 12
            },
            {
                "name": "比目魚",
                "jpName": "ヒラメ",
                "checked": false,
                "season": "冬",
                "MaxCM": 60,
                "id": 13
            },
            {
                "name": "毒虹鱒魚/虹色魚",
                "jpName": "ドクニジマス",
                "checked": false,
                "season": "冬",
                "MaxCM": 60,
                "id": 14
            },
            {
                "name": "烏賊",
                "jpName": "イカ",
                "checked": false,
                "season": "全",
                "MaxCM": 60,
                "buy": 800,
                "sell": 80,
                "id": 15
            },
            {
                "name": "紅葉比目魚",
                "jpName": "モミジヒラメ",
                "checked": false,
                "season": "秋",
                "MaxCM": 60,
                "buy": 28000,
                "sell": 2800,
                "id": 16
            },
            {
                "name": "鯛魚",
                "jpName": "タイ",
                "checked": false,
                "season": "秋",
                "MaxCM": 60,
                "buy": 4800,
                "sell": 480,
                "id": 17
            },
            {
                "name": "秋刀魚",
                "jpName": "サンマ",
                "checked": false,
                "season": "秋",
                "MaxCM": 60,
                "buy": 400,
                "sell": 40,
                "id": 18
            },
            {
                "name": "鯖魚/鮐魚",
                "jpName": "サバ",
                "checked": false,
                "season": "秋",
                "MaxCM": 60,
                "buy": 1300,
                "sell": 130,
                "id": 19
            },
            {
                "name": "龍蝦",
                "jpName": "ロブスター",
                "checked": false,
                "season": "夏",
                "MaxCM": 60,
                "id": 20
            },
            {
                "name": "鯽魚",
                "jpName": "ヘラブナ",
                "checked": false,
                "season": "夏",
                "MaxCM": 60,
                "id": 21
            },
            {
                "name": "斑烏賊/南國章魚",
                "jpName": "ジャマイカ",
                "checked": false,
                "season": "夏",
                "MaxCM": 60,
                "buy": 74000,
                "sell": 7400,
                "id": 22
            },
            {
                "name": "鰈魚",
                "jpName": "カレイ",
                "checked": false,
                "season": "夏",
                "MaxCM": 60,
                "buy": 3400,
                "sell": 340,
                "id": 23
            },
            {
                "name": "沙比目魚",
                "jpName": "砂ヒラメ",
                "checked": false,
                "MaxCM": 60,
                "id": 24
            },
            {
                "name": "金槍魚",
                "jpName": "マグロ",
                "checked": false,
                "season": "冬",
                "MaxCM": 100,
                "id": 25
            },
            {
                "name": "鰤魚",
                "jpName": "ブリ",
                "checked": false,
                "season": "冬",
                "MaxCM": 100,
                "buy": 45000,
                "sell": 4500,
                "id": 26
            },
            {
                "name": "銀鯛",
                "jpName": "カガヤキタイ",
                "checked": false,
                "season": "冬",
                "MaxCM": 100,
                "buy": 100000,
                "sell": 10000,
                "id": 27
            },
            {
                "name": "哲羅魚",
                "jpName": "イトウ",
                "checked": false,
                "season": "冬",
                "MaxCM": 100,
                "id": 28
            },
            {
                "name": "鮭魚",
                "jpName": "サケ",
                "checked": false,
                "season": "秋",
                "MaxCM": 100,
                "id": 29
            },
            {
                "name": "鰹魚",
                "jpName": "カツオ",
                "checked": false,
                "season": "秋",
                "MaxCM": 100,
                "buy": 4200,
                "sell": 420,
                "id": 30
            },
            {
                "name": "巖石魚",
                "jpName": "巖石魚",
                "checked": false,
                "MaxCM": 100,
                "id": 31
            },
            {
                "name": "心跳鯛魚",
                "jpName": "トキメキタイ",
                "checked": false,
                "MaxCM": 100,
                "buy": 38000,
                "sell": 3800,
                "id": 32
            }
        ]
    },
    {
        "category": "收集品",
        "tab": "collectionTab",
        "active": false,
        "list": [
            {
                "name": "鐵屑",
                "jpName": "クズ鉄",
                "checked": false,
                "buy": 60,
                "sell": 20,
                "id": 1
            },
            {
                "name": "莫可棉/軟綿綿棉",
                "jpName": "モコ綿",
                "checked": false,
                "buy": 80,
                "sell": 20,
                "getItem": "モコモコを倒す",
                "id": 2
            },
            {
                "name": "獸人的破布",
                "jpName": "オークのボロ布",
                "checked": false,
                "buy": 80,
                "sell": 40,
                "id": 3
            },
            {
                "name": "蟲皮",
                "jpName": "蟲の皮",
                "checked": false,
                "buy": 120,
                "sell": 40,
                "id": 4
            },
            {
                "name": "鐵",
                "jpName": "鉄",
                "checked": false,
                "buy": 200,
                "sell": 50,
                "id": 5
            },
            {
                "name": "牧草",
                "jpName": "牧草",
                "checked": false,
                "buy": 240,
                "sell": 60,
                "id": 6
            },
            {
                "name": "結實的蜘蛛絲",
                "jpName": "丈夫なクモ糸",
                "checked": false,
                "buy": 160,
                "sell": 80,
                "id": 7
            },
            {
                "name": "生鏽的箭頭",
                "jpName": "さびた矢尻",
                "checked": false,
                "buy": 300,
                "sell": 80,
                "id": 8
            },
            {
                "name": "銅",
                "jpName": "銅",
                "checked": false,
                "buy": 360,
                "sell": 90,
                "id": 9
            },
            {
                "name": "愛之結晶",
                "jpName": "愛の結晶",
                "checked": false,
                "buy": 1000,
                "sell": 100,
                "getItem": "ピンクのゲートを破壊する",
                "id": 10
            },
            {
                "name": "暗之結晶",
                "jpName": "闇の結晶",
                "checked": false,
                "buy": 1000,
                "sell": 100,
                "getItem": "黒いゲートを破壊する",
                "id": 11
            },
            {
                "name": "光之結晶",
                "jpName": "光の結晶",
                "checked": false,
                "buy": 1000,
                "sell": 100,
                "getItem": "黃色のゲートを破壊する",
                "id": 12
            },
            {
                "name": "地之結晶",
                "jpName": "地の結晶",
                "checked": false,
                "buy": 1000,
                "sell": 100,
                "id": 13
            },
            {
                "name": "漂亮的蜘蛛絲",
                "jpName": "キレイなクモ糸",
                "checked": false,
                "buy": 220,
                "sell": 110,
                "id": 14
            },
            {
                "name": "戰士之證",
                "jpName": "戦士の証",
                "checked": false,
                "buy": 560,
                "sell": 110,
                "id": 15
            },
            {
                "name": "昆蟲的下顎",
                "jpName": "昆蟲のアゴ",
                "checked": false,
                "buy": 280,
                "sell": 120,
                "id": 16
            },
            {
                "name": "海盜哥布林的布",
                "jpName": "海賊ゴブリンの布",
                "checked": false,
                "buy": 480,
                "sell": 120,
                "id": 17
            },
            {
                "name": "軟毛",
                "jpName": "ふわ毛",
                "checked": false,
                "buy": 500,
                "sell": 120,
                "id": 18
            },
            {
                "name": "豹爪",
                "jpName": "豹の爪",
                "checked": false,
                "buy": 360,
                "sell": 140,
                "id": 19
            },
            {
                "name": "結實的藤",
                "jpName": "丈夫なツル",
                "checked": false,
                "buy": 290,
                "sell": 150,
                "id": 20
            },
            {
                "name": "植物的莖",
                "jpName": "植物の莖",
                "checked": false,
                "buy": 300,
                "sell": 150,
                "id": 21
            },
            {
                "name": "毛皮",
                "jpName": "毛皮",
                "checked": false,
                "buy": 280,
                "sell": 160,
                "id": 22
            },
            {
                "name": "蘑菇孢子",
                "jpName": "キノコの胞子",
                "checked": false,
                "buy": 260,
                "sell": 180,
                "id": 23
            },
            {
                "name": "漂亮的蟲皮",
                "jpName": "キレイな蟲の皮",
                "checked": false,
                "buy": 280,
                "sell": 180,
                "id": 24
            },
            {
                "name": "骨膠",
                "jpName": "にかわ",
                "checked": false,
                "buy": 500,
                "sell": 180,
                "id": 25
            },
            {
                "name": "蝎子的鉗",
                "jpName": "サソリのはさみ",
                "checked": false,
                "buy": 340,
                "sell": 190,
                "id": 26
            },
            {
                "name": "鬥牛之角",
                "jpName": "闘牛の角",
                "checked": false,
                "buy": 760,
                "sell": 190,
                "id": 27
            },
            {
                "name": "錘子的碎片",
                "jpName": "ハンマーの破片",
                "checked": false,
                "buy": 400,
                "sell": 200,
                "id": 28
            },
            {
                "name": "火之結晶",
                "jpName": "火の結晶",
                "checked": false,
                "buy": 1100,
                "sell": 200,
                "getItem": "赤色のゲートを破壊する",
                "id": 29
            },
            {
                "name": "水之結晶",
                "jpName": "水の結晶",
                "checked": false,
                "buy": 1100,
                "sell": 200,
                "id": 30
            },
            {
                "name": "風之結晶",
                "jpName": "風の結晶",
                "checked": false,
                "buy": 1100,
                "sell": 200,
                "getItem": "緑色のゲートを破壊する",
                "id": 31
            },
            {
                "name": "堅固的角",
                "jpName": "強固な角",
                "checked": false,
                "buy": 380,
                "sell": 220,
                "id": 32
            },
            {
                "name": "哥布林的繃帶",
                "jpName": "ゴブリンの包帯",
                "checked": false,
                "buy": 440,
                "sell": 220,
                "id": 33
            },
            {
                "name": "鳥之羽",
                "jpName": "鳥の羽",
                "checked": false,
                "buy": 660,
                "sell": 240,
                "id": 34
            },
            {
                "name": "蝎子的尾巴",
                "jpName": "サソリの尻尾",
                "checked": false,
                "buy": 400,
                "sell": 250,
                "id": 35
            },
            {
                "name": "射手的火藥",
                "jpName": "射手の発火薬",
                "checked": false,
                "buy": 640,
                "sell": 250,
                "id": 36
            },
            {
                "name": "植物的根",
                "jpName": "植物の根",
                "checked": false,
                "buy": 740,
                "sell": 260,
                "id": 37
            },
            {
                "name": "銀",
                "jpName": "銀",
                "checked": false,
                "buy": 1040,
                "sell": 260,
                "id": 38
            },
            {
                "name": "巨人之爪",
                "jpName": "巨人の爪",
                "checked": false,
                "buy": 480,
                "sell": 280,
                "id": 39
            },
            {
                "name": "龜殼",
                "jpName": "カメのこうら",
                "checked": false,
                "buy": 820,
                "sell": 280,
                "getItem": "トータスを倒す",
                "id": 40
            },
            {
                "name": "紫水晶",
                "jpName": "アメジスト",
                "checked": false,
                "buy": 1200,
                "sell": 300,
                "id": 41
            },
            {
                "name": "小結晶",
                "jpName": "小さな結晶",
                "checked": false,
                "buy": 2100,
                "sell": 300,
                "getItem": "スライムを倒す",
                "id": 42
            },
            {
                "name": "骷髏",
                "jpName": "ドクロ",
                "checked": false,
                "buy": 2580,
                "sell": 300,
                "id": 43
            },
            {
                "name": "巨人的手套",
                "jpName": "巨人の手袋",
                "checked": false,
                "buy": 520,
                "sell": 320,
                "id": 44
            },
            {
                "name": "絲綢",
                "jpName": "シルクの布",
                "checked": false,
                "buy": 1280,
                "sell": 320,
                "id": 45
            },
            {
                "name": "狼牙",
                "jpName": "狼の牙",
                "checked": false,
                "buy": 1320,
                "sell": 330,
                "id": 46
            },
            {
                "name": "魔法師之粉",
                "jpName": "魔法使いの粉",
                "checked": false,
                "buy": 1040,
                "sell": 360,
                "id": 47
            },
            {
                "name": "上質的毛皮",
                "jpName": "上質の毛皮",
                "checked": false,
                "buy": 1440,
                "sell": 360,
                "id": 48
            },
            {
                "name": "維京護肩",
                "jpName": "バイキングの肩當て",
                "checked": false,
                "buy": 1120,
                "sell": 380,
                "id": 49
            },
            {
                "name": "魔力之結晶",
                "jpName": "魔力の結晶",
                "checked": false,
                "buy": 1200,
                "sell": 400,
                "id": 50
            },
            {
                "name": "金",
                "jpName": "金",
                "checked": false,
                "buy": 1720,
                "sell": 430,
                "id": 51
            },
            {
                "name": "毒粉",
                "jpName": "毒の粉",
                "checked": false,
                "buy": 2340,
                "sell": 430,
                "id": 52
            },
            {
                "name": "古代魚之骨",
                "jpName": "古代魚の骨",
                "checked": false,
                "buy": 1480,
                "sell": 445,
                "getItem": "シーラ",
                "id": 53
            },
            {
                "name": "浮幽靈的頭巾",
                "jpName": "浮遊霊の頭巾",
                "checked": false,
                "buy": 1660,
                "sell": 490,
                "id": 54
            },
            {
                "name": "軟軟的毛",
                "jpName": "ふわふわ毛",
                "checked": false,
                "buy": 2000,
                "sell": 500,
                "id": 55
            },
            {
                "name": "魔人之角",
                "jpName": "魔人の角",
                "checked": false,
                "buy": 2160,
                "sell": 540,
                "id": 56
            },
            {
                "name": "紅寶石",
                "jpName": "ルビー",
                "checked": false,
                "buy": 2000,
                "sell": 550,
                "id": 57
            },
            {
                "name": "綠寶石",
                "jpName": "エメラルド",
                "checked": false,
                "buy": 1800,
                "sell": 580,
                "id": 58
            },
            {
                "name": "惡魔之血",
                "jpName": "悪魔の血",
                "checked": false,
                "buy": 2320,
                "sell": 580,
                "id": 59
            },
            {
                "name": "壞掉的柄",
                "jpName": "壊れた柄",
                "checked": false,
                "buy": 2140,
                "sell": 610,
                "id": 60
            },
            {
                "name": "壞掉的木箱",
                "jpName": "壊れた木箱",
                "checked": false,
                "buy": 2300,
                "sell": 650,
                "getItem": "パックンボックスを倒す",
                "id": 61
            },
            {
                "name": "軟軟綿綿的毛",
                "jpName": "ふわふわモフモフ毛",
                "checked": false,
                "buy": 2800,
                "sell": 700,
                "id": 62
            },
            {
                "name": "白金",
                "jpName": "プラチナ",
                "checked": false,
                "buy": 3000,
                "sell": 750,
                "id": 63
            },
            {
                "name": "龍牙",
                "jpName": "ドラゴンの牙",
                "checked": false,
                "buy": 3160,
                "sell": 790,
                "getItem": "ミニドラゴン",
                "id": 64
            },
            {
                "name": "妖精之粉",
                "jpName": "妖精の粉",
                "checked": false,
                "buy": 2900,
                "sell": 800,
                "id": 65
            },
            {
                "name": "海藍寶石",
                "jpName": "アクアマリン",
                "checked": false,
                "buy": 3000,
                "sell": 890,
                "id": 66
            },
            {
                "name": "毛線球",
                "jpName": "毛糸玉",
                "checked": false,
                "buy": 4800,
                "sell": 900,
                "id": 67
            },
            {
                "name": "藍寶石",
                "jpName": "サファイア",
                "checked": false,
                "buy": 3600,
                "sell": 1100,
                "id": 68
            },
            {
                "name": "鑽石",
                "jpName": "ダイヤモンド",
                "checked": false,
                "buy": 5600,
                "sell": 1800,
                "id": 69
            },
            {
                "name": "貍貓樹葉",
                "jpName": "たぬきの葉っぱ",
                "checked": false,
                "buy": 9000,
                "sell": 2500,
                "getItem": "タヌゴローを倒す",
                "id": 70
            },
            {
                "name": "魚主之鱗/努西之鱗",
                "jpName": "ヌッシーのうろこ",
                "checked": false,
                "buy": 30000,
                "sell": 3000,
                "getItem": "アクナビートを倒す，アクナ湖で釣りをしていると稀に釣れる",
                "id": 71
            },
            {
                "name": "豪邁胸毛",
                "jpName": "グレートな胸毛",
                "checked": false,
                "buy": 9600,
                "sell": 3600,
                "getItem": "グレーターデーモンを倒す",
                "id": 72
            },
            {
                "name": "鸚鵡螺化石",
                "jpName": "アンモナイト",
                "checked": false,
                "buy": 16800,
                "sell": 3800,
                "getItem": "オクトパイレーツを倒す",
                "id": 73
            },
            {
                "name": "獅子的藍毛",
                "jpName": "獅子の青毛",
                "checked": false,
                "buy": 22500,
                "sell": 4000,
                "getItem": "きのとを倒す",
                "id": 74
            },
            {
                "name": "獅子的紅毛",
                "jpName": "獅子の赤毛",
                "checked": false,
                "buy": 22500,
                "sell": 4000,
                "getItem": "ひのえを倒す",
                "id": 75
            },
            {
                "name": "會動的樹枝",
                "jpName": "動く枝",
                "checked": false,
                "buy": 150000,
                "sell": 4200,
                "getItem": "デットツリーを倒す",
                "id": 76
            },
            {
                "name": "冰之鼻",
                "jpName": "氷の鼻",
                "checked": false,
                "buy": 26100,
                "sell": 4400,
                "getItem": "クリスタルマンモスを倒す",
                "id": 77
            },
            {
                "name": "電氣結晶",
                "jpName": "電気の結晶",
                "checked": false,
                "buy": 160000,
                "sell": 4400,
                "getItem": "ウーパードラゴンを倒す",
                "id": 78
            },
            {
                "name": "歌之小瓶",
                "jpName": "歌の小ビン",
                "checked": false,
                "buy": 170000,
                "sell": 4600,
                "getItem": "セイレーンを倒す",
                "id": 79
            },
            {
                "name": "怪力石版/格勒姆石版",
                "jpName": "ゴーレムの石版",
                "checked": false,
                "buy": 180000,
                "sell": 4800,
                "id": 80
            },
            {
                "name": "龍骨",
                "jpName": "竜の骨",
                "checked": false,
                "buy": 24000,
                "sell": 5000,
                "getItem": "エンシェントボーンを倒す",
                "id": 81
            },
            {
                "name": "奇美拉之尾",
                "jpName": "キメラのしっぽ",
                "checked": false,
                "buy": 14400,
                "sell": 5500,
                "getItem": "キメラを倒す",
                "id": 82
            },
            {
                "name": "冰壁的碎片",
                "jpName": "氷壁のかけら",
                "checked": false,
                "buy": 66000,
                "sell": 6000,
                "getItem": "デスウォールを倒す",
                "id": 83
            },
            {
                "name": "格利莫亞之鱗",
                "jpName": "グリモアのうろこ",
                "checked": false,
                "buy": 144000,
                "sell": 7000,
                "getItem": "グリモアを倒す",
                "id": 84
            },
            {
                "name": "水龍的羽鰭",
                "jpName": "水竜の羽びれ",
                "checked": false,
                "buy": 90000,
                "sell": 8400,
                "getItem": "アクナビートを倒す",
                "id": 85
            },
            {
                "name": "地龍之鱗",
                "jpName": "地竜のうろこ",
                "checked": false,
                "buy": 190000,
                "sell": 9000,
                "id": 86
            },
            {
                "name": "火龍之鱗",
                "jpName": "火竜のうろこ",
                "checked": false,
                "buy": 200000,
                "sell": 10000,
                "id": 87
            }
        ]
    },
    {
        "category": "失敗作、垃圾、其他",
        "tab": "other",
        "active": false,
        "list": [
            {
                "name": "失敗作",
                "jpName": "失敗作",
                "checked": false,
                "sp": [
                    "HP-20%",
                    "HP上限-10%",
                    "RP上限-10%",
                    "力量-10%",
                    "體力-10%",
                    "智力-10%"
                ],
                "buy": 10,
                "sell": 2,
                "id": 1
            },
            {
                "name": "超失敗作",
                "jpName": "超失敗作",
                "checked": false,
                "sp": [
                    "HP-80%",
                    "RP上限-25%",
                    "力量-25%",
                    "體力-25%",
                    "智力-25%"
                ],
                "buy": 100,
                "sell": 50,
                "id": 2
            },
            {
                "name": "稀有的空罐子",
                "jpName": "レアなあきかん",
                "checked": false,
                "buy": 200,
                "sell": 100,
                "id": 3
            },
            {
                "name": "長靴",
                "jpName": "ながぐつ",
                "checked": false,
                "buy": 60,
                "sell": 30,
                "id": 4
            },
            {
                "name": "空罐子",
                "jpName": "あきかん",
                "checked": false,
                "buy": 5,
                "sell": 1,
                "id": 5
            },
            {
                "name": "木材",
                "jpName": "木材",
                "checked": false,
                "buy": 80,
                "sell": 40,
                "id": 6
            },
            {
                "name": "樹枝",
                "jpName": "枝",
                "checked": false,
                "buy": 40,
                "sell": 20,
                "id": 7
            },
            {
                "name": "石頭",
                "jpName": "石",
                "checked": false,
                "buy": 10,
                "sell": 2,
                "id": 8
            }
        ]
    }
]